pyelectrica/__init__.py
pyelectrica/pyelectrica.py
pyelectrica-1.1.4.post2.dist-info/LICENSE
pyelectrica-1.1.4.post2.dist-info/METADATA
pyelectrica-1.1.4.post2.dist-info/WHEEL
pyelectrica-1.1.4.post2.dist-info/top_level.txt
pyelectrica-1.1.4.post2.dist-info/RECORD
