Metadata-Version: 2.1
Name: pyelectrica
Version: 1.1.4.post2
Summary: Módulo PyElectrica, útil para resolver problemas específicos     de Máquinas y Circuitos Eléctricos, así como de Instalaciones Eléctricas
Home-page: https://pyelectrica.ml
Author: Isai Aragón P.
Author-email: isaix25@gmail.com
License: UNKNOWN
Platform: UNKNOWN
Classifier: Programming Language :: Python :: 3.5
Classifier: Programming Language :: Python :: 3.6
Classifier: Programming Language :: Python :: 3.7
Classifier: License :: OSI Approved :: MIT License
Classifier: Operating System :: OS Independent
Classifier: Development Status :: 5 - Production/Stable
Classifier: Natural Language :: Spanish
Classifier: Topic :: Education
Classifier: Topic :: Scientific/Engineering
Requires-Python: >=3.5
Requires-Dist: numpy
Requires-Dist: matplotlib
Requires-Dist: scipy
Requires-Dist: SchemDraw
